[
  {
    "SourceFile": "./DSCF5344-topaz.jpg",
    "XMPToolkit": "XMP Core 6.0.0",
    "CreateDate": "2024:01:27 16:36:03-08:00",
    "Headline": "Mirror Pond",
    "Lens": "Fujifilm Fujinon XF150-600mmF5.6-8 R LM OIS WR",
    "FlashCompensation": 0,
    "DateCreated": "2024:01:27 16:36:03-08:00",
    "Rights": "",
    "Make": "FUJIFILM",
    "Model": "X-H2S",
    "XResolution": 72,
    "YResolution": 72,
    "ResolutionUnit": "inches",
    "Software": "Topaz Photo AI 2.2.2 (Macintosh)",
    "ExposureTime": "1/180",
    "FNumber": 8.0,
    "ExposureProgram": "Aperture-priority AE",
    "ISO": 3200,
    "SensitivityType": "Standard Output Sensitivity",
    "ExifVersion": "0230",
    "DateTimeOriginal": "2024:01:27 16:36:03",
    "CreateDate": "2024:01:27 16:36:03",
    "ComponentsConfiguration": "Y, Cb, Cr, -",
    "ShutterSpeedValue": "1/180",
    "ApertureValue": 8.0,
    "BrightnessValue": 3.94,
    "ExposureCompensation": 0,
    "MaxApertureValue": 5.7,
    "MeteringMode": "Multi-segment",
    "LightSource": "Unknown",
    "Flash": "No Flash",
    "FocalLength": "600.0 mm",
    "FlashpixVersion": "0100",
    "ColorSpace": "sRGB",
    "ExifImageWidth": 2000,
    "ExifImageHeight": 1599,
    "FocalPlaneXResolution": 1882,
    "FocalPlaneYResolution": 1882,
    "FocalPlaneResolutionUnit": "cm",
    "SensingMethod": "One-chip color area",
    "FileSource": "Digital Camera",
    "SceneType": "Directly photographed",
    "CustomRendered": "Normal",
    "ExposureMode": "Auto",
    "WhiteBalance": "Auto",
    "FocalLengthIn35mmFormat": "900 mm",
    "SceneCaptureType": "Standard",
    "Sharpness": "Hard",
    "SubjectDistanceRange": "Unknown",
    "SerialNumber": "2CA01017",
    "LensInfo": "600mm f/5.656854153",
    "LensMake": "FUJIFILM",
    "LensModel": "Fujifilm Fujinon XF150-600mmF5.6-8 R LM OIS WR",
    "LensSerialNumber": "35A02272",
    "CodedCharacterSet": "UTF8",
    "ApplicationRecordVersion": 2,
    "DigitalCreationDate": "2024:01:27",
    "DigitalCreationTime": "16:36:03-08:00",
    "DateCreated": "2024:01:27",
    "TimeCreated": "16:36:03-08:00"
  }
]
