{
  "SourceFile": "/Users/kai/projects/Github/conragan/content/photography/landscape/davenport-milky-way/DSCF2221 1.jpg",
  "XMPToolkit": "XMP Core 5.5.0",
  "CreatorTool": "Capture One Macintosh",
  "Lens": "21 mm f/--",
  "FlashCompensation": 0,
  "DateCreated": "2024:08:31 21:57:52-07:00",
  "LegacyIPTCDigest": "78DFF8C56A5B5898B389A5D064F682D6",
  "Rights": ",                                                                                                                                                                                                                                                               ",
  "Headline": "Davenport Milky Way",
  "Make": "FUJIFILM",
  "Model": "X-H2S",
  "XResolution": 72,
  "YResolution": 72,
  "ResolutionUnit": "inches",
  "Software": "Capture One Macintosh",
  "Copyright": "",
  "ExposureTime": 20,
  "FNumber": 2.0,
  "ExposureProgram": "Manual",
  "ISO": 6400,
  "SensitivityType": "Standard Output Sensitivity",
  "ExifVersion": "0230",
  "DateTimeOriginal": "2024:08:31 21:57:52",
  "CreateDate": "2024:08:31 21:57:52",
  "ShutterSpeedValue": 20,
  "ApertureValue": 1.0,
  "BrightnessValue": -17.95,
  "ExposureCompensation": 0,
  "MeteringMode": "Multi-segment",
  "LightSource": "Unknown",
  "Flash": "No Flash",
  "FocalLength": "21.0 mm",
  "ExifImageWidth": 1365,
  "ExifImageHeight": 2048,
  "FocalPlaneXResolution": 1882,
  "FocalPlaneYResolution": 1882,
  "FocalPlaneResolutionUnit": "cm",
  "SensingMethod": "One-chip color area",
  "FileSource": "Digital Camera",
  "SceneType": "Directly photographed",
  "CustomRendered": "Normal",
  "ExposureMode": "Manual",
  "WhiteBalance": "Auto",
  "FocalLengthIn35mmFormat": "18mm",
  "SceneCaptureType": "Standard",
  "Sharpness": "Normal",
  "SubjectDistanceRange": "Unknown",
  "SerialNumber": "2CA01017",
  "LensInfo": "Rokinon 12mm F.20",
  "LensModel": "Rokinon 12mm F.20",
  "Compression": "JPEG (old-style)",
  "ThumbnailOffset": 1090,
  "ThumbnailLength": 1162,
  "ThumbnailImage": "(Binary data 1162 bytes, use -b option to extract)",
  "CodedCharacterSet": "UTF8",
  "ApplicationRecordVersion": 4,
  "TimeCreated": "21:57:52-07:00",
  "DigitalCreationDate": "2024:08:31",
  "DigitalCreationTime": "21:57:52-07:00",
  "CopyrightNotice": "                                                                                                                                "
}

